pylazypdf-0.1.0.dist-info/METADATA
pylazypdf-0.1.0.dist-info/WHEEL
pylazypdf/__init__.py
pylazypdf/pylazypdf.cpython-311-x86_64-linux-gnu.so
pylazypdf-0.1.0.dist-info/RECORD
